monkstools/__init__.py
monkstools/d1_data_map_customer_media.csv
monkstools/d2_data_map_perfer_product_customer.csv
monkstools/d3_data_map_delivery_cost_media.csv
monkstools/d4_data_map_product_costomerType.csv
monkstools/m1_get_customer_media.py
monkstools/m2_get_product.py
monkstools/m3_delivery_cost_media.py
monkstools/m4_product_costomerType.py
monkstools/main_roi.py
monkstools/person_group.py
monkstools/product_preference.py
monkstools/roi_calculator.py
monkstools/secondary_preference.py
monkstools/top_module.py
monkstools/transmission_cost.py
monkstools-0.15.dist-info/LICENSE.txt
monkstools-0.15.dist-info/METADATA
monkstools-0.15.dist-info/WHEEL
monkstools-0.15.dist-info/top_level.txt
monkstools-0.15.dist-info/RECORD
