Metadata-Version: 2.1
Name: monkstools
Version: 0.15
Summary: Tools for the Monks advertising platform
Home-page: https://github.com/williampolicy/monkstools
Author: xiaowen kang
Author-email: kangxiaowen@gmail.com
License: UNKNOWN
Platform: UNKNOWN
Classifier: License :: OSI Approved :: MIT License
Classifier: Programming Language :: Python :: 3
Classifier: Programming Language :: Python :: 3.7
